findsym/__init__.py
findsym/_version.py
findsym/core.py
findsym-0.1.1.dist-info/licenses/LICENSE
findsym-0.1.1.dist-info/METADATA
findsym-0.1.1.dist-info/WHEEL
findsym-0.1.1.dist-info/entry_points.txt
findsym-0.1.1.dist-info/top_level.txt
findsym-0.1.1.dist-info/RECORD
