Metadata-Version: 2.4
Name: findsym
Version: 0.1.1
Summary: FINDSYM: Symmetry detection for crystal structures
Home-page: https://github.com/AniruthAnanth/findsympy
Author: Aniruth Ananthanarayanan
Author-email: Aniruth Ananthanarayanan <aniruthananthanarayanan@my.unt.edu>
Maintainer-email: Aniruth Ananthanarayanan <aniruthananthanarayanan@my.unt.edu>
License: MIT
Project-URL: Homepage, https://github.com/AniruthAnanth/findsympy
Project-URL: Bug Reports, https://github.com/AniruthAnanth/findsympy/issues
Project-URL: Source, https://github.com/AniruthAnanth/findsympy
Keywords: crystallography,symmetry,spglib,materials-science
Classifier: Development Status :: 4 - Beta
Classifier: Intended Audience :: Science/Research
Classifier: License :: OSI Approved :: MIT License
Classifier: Operating System :: OS Independent
Classifier: Programming Language :: Python :: 3
Classifier: Programming Language :: Python :: 3.8
Classifier: Programming Language :: Python :: 3.9
Classifier: Programming Language :: Python :: 3.10
Classifier: Programming Language :: Python :: 3.11
Classifier: Topic :: Scientific/Engineering :: Chemistry
Classifier: Topic :: Scientific/Engineering :: Physics
Requires-Python: >=3.8
License-File: LICENSE
Requires-Dist: numpy>=1.18.0
Requires-Dist: ase>=3.20.0
Requires-Dist: spglib>=1.16.0
Provides-Extra: visualization
Requires-Dist: matplotlib>=3.3.0; extra == "visualization"
Provides-Extra: dev
Requires-Dist: pytest>=6.0; extra == "dev"
Requires-Dist: pytest-cov; extra == "dev"
Requires-Dist: black; extra == "dev"
Requires-Dist: flake8; extra == "dev"
Requires-Dist: isort; extra == "dev"
Dynamic: author
Dynamic: home-page
Dynamic: license-file
Dynamic: requires-python
